Metadata-Version: 2.1
Name: APScheduler-ng
Version: 0.0.1
Summary: In-process task scheduler with Cron-like capabilities
Home-page: https://github.com/agronholm/apscheduler
Author: Alex Grönholm
Author-email: apscheduler@nextday.fi
License: MIT
Keywords: scheduling cron
Platform: UNKNOWN
Classifier: Development Status :: 5 - Production/Stable
Classifier: Intended Audience :: Developers
Classifier: License :: OSI Approved :: MIT License
Classifier: Programming Language :: Python
Classifier: Programming Language :: Python :: 2.7
Classifier: Programming Language :: Python :: 3
Classifier: Programming Language :: Python :: 3.4
Classifier: Programming Language :: Python :: 3.5
Classifier: Programming Language :: Python :: 3.6
Classifier: Programming Language :: Python :: 3.7
Requires-Dist: setuptools (>=0.7)
Requires-Dist: six (>=1.4.0)
Requires-Dist: pytz
Requires-Dist: tzlocal (>=1.2)
Requires-Dist: futures ; python_version == "2.7"
Requires-Dist: funcsigs ; python_version == "2.7"
Provides-Extra: asyncio
Requires-Dist: trollius ; (python_version == "2.7") and extra == 'asyncio'
Provides-Extra: doc
Requires-Dist: sphinx ; extra == 'doc'
Requires-Dist: sphinx-rtd-theme ; extra == 'doc'
Provides-Extra: gevent
Requires-Dist: gevent ; extra == 'gevent'
Provides-Extra: mongodb
Requires-Dist: pymongo (>=2.8) ; extra == 'mongodb'
Provides-Extra: redis
Requires-Dist: redis (>=3.0) ; extra == 'redis'
Provides-Extra: rethinkdb
Requires-Dist: rethinkdb (>=2.4.0) ; extra == 'rethinkdb'
Provides-Extra: sqlalchemy
Requires-Dist: sqlalchemy (>=0.8) ; extra == 'sqlalchemy'
Provides-Extra: testing
Requires-Dist: pytest ; extra == 'testing'
Requires-Dist: pytest-cov ; extra == 'testing'
Requires-Dist: pytest-tornado5 ; extra == 'testing'
Requires-Dist: mock ; (python_version == "2.7") and extra == 'testing'
Requires-Dist: pytest-asyncio (<0.6) ; (python_version == "3.4") and extra == 'testing'
Requires-Dist: pytest-asyncio ; (python_version >= "3.5") and extra == 'testing'
Provides-Extra: tornado
Requires-Dist: tornado (>=4.3) ; extra == 'tornado'
Provides-Extra: twisted
Requires-Dist: twisted ; extra == 'twisted'
Provides-Extra: zookeeper
Requires-Dist: kazoo ; extra == 'zookeeper'
